steamleaderboards/__init__.py
steamleaderboards/__main__.py
steamleaderboards-1.1.4.dist-info/METADATA
steamleaderboards-1.1.4.dist-info/WHEEL
steamleaderboards-1.1.4.dist-info/entry_points.txt
steamleaderboards-1.1.4.dist-info/licenses/LICENSE.txt
steamleaderboards-1.1.4.dist-info/RECORD
