Metadata-Version: 2.4
Name: steamleaderboards
Version: 1.1.4
Summary: Retrieve and parse Steam leaderboards
License-Expression: MIT
License-File: LICENSE.txt
Keywords: steam,leaderboards,csv,xml,valve
Author: Stefano Pigozzi
Author-email: me@steffo.eu
Maintainer: Stefano Pigozzi
Maintainer-email: me@steffo.eu
Requires-Python: >=3.8,<4.0
Classifier: Programming Language :: Python :: 3
Classifier: Programming Language :: Python :: 3.8
Classifier: Programming Language :: Python :: 3.9
Classifier: Programming Language :: Python :: 3.10
Classifier: Programming Language :: Python :: 3.11
Classifier: Programming Language :: Python :: 3.12
Classifier: Programming Language :: Python :: 3.13
Classifier: Development Status :: 7 - Inactive
Classifier: Environment :: Console
Classifier: Intended Audience :: Developers
Classifier: Intended Audience :: Science/Research
Classifier: License :: OSI Approved :: MIT License
Classifier: Operating System :: OS Independent
Classifier: Topic :: Internet
Requires-Dist: beautifulsoup4 (>=4.12.3,<5.0.0)
Requires-Dist: lxml (>=6.0.0,<7.0.0)
Requires-Dist: requests (>=2.32.2,<3.0.0)
Project-URL: Documentation, https://forge.steffo.eu/steffo/steamleaderboards/wiki
Project-URL: Issues, https://forge.steffo.eu/steffo/steamleaderboards/issues
Project-URL: Source, https://forge.steffo.eu/steffo/steamleaderboards
